gitlab_watchman/__init__.py
gitlab_watchman/__main__.py
gitlab_watchman/clients/__init__.py
gitlab_watchman/clients/gitlab_client.py
gitlab_watchman/exceptions.py
gitlab_watchman/loggers.py
gitlab_watchman/models/__init__.py
gitlab_watchman/models/blob.py
gitlab_watchman/models/commit.py
gitlab_watchman/models/file.py
gitlab_watchman/models/group.py
gitlab_watchman/models/issue.py
gitlab_watchman/models/merge_request.py
gitlab_watchman/models/milestone.py
gitlab_watchman/models/note.py
gitlab_watchman/models/project.py
gitlab_watchman/models/signature.py
gitlab_watchman/models/snippet.py
gitlab_watchman/models/user.py
gitlab_watchman/models/wiki_blob.py
gitlab_watchman/signature_downloader.py
gitlab_watchman/utils.py
gitlab_watchman/watchman_processor.py
gitlab_watchman-3.1.0.dist-info/LICENSE
gitlab_watchman-3.1.0.dist-info/METADATA
gitlab_watchman-3.1.0.dist-info/WHEEL
gitlab_watchman-3.1.0.dist-info/entry_points.txt
gitlab_watchman-3.1.0.dist-info/RECORD
