Metadata-Version: 2.1
Name: gitlab-watchman
Version: 3.1.0
Summary: Finding exposed secrets and personal data in GitLab
Home-page: https://github.com/PaperMtn/gitlab-watchman
License: GPL-3.0
Keywords: audit,dlp,gitlab,gitlab-watchman,watchman,blue-team,red-team,threat-hunting
Author: PaperMtn
Author-email: papermtn@protonmail.com
Requires-Python: >=3.10
Classifier: Intended Audience :: Information Technology
Classifier: License :: OSI Approved :: GNU General Public License v3 (GPLv3)
Classifier: Programming Language :: Python :: 3
Classifier: Programming Language :: Python :: 3.10
Classifier: Programming Language :: Python :: 3.11
Classifier: Programming Language :: Python :: 3.12
Classifier: Programming Language :: Python :: 3.13
Requires-Dist: colorama (>=0.4.6,<0.5.0)
Requires-Dist: python-gitlab (>=5.0.0,<6.0.0)
Requires-Dist: pytz (>=2024.2,<2025.0)
Requires-Dist: pyyaml (>=6.0.2,<7.0.0)
Requires-Dist: requests (>=2.32.3,<3.0.0)
Project-URL: Blog, https://papermtn.co.uk/category/tools/gitlab-watchman/
Project-URL: Repository, https://github.com/PaperMtn/gitlab-watchman
